{
  "id": "3120276",
  "name": "vh-saas",
  "font_family": "vh-saas-iconfont",
  "css_prefix_text": "vh-saas-",
  "description": "",
  "glyphs": [
    {
      "icon_id": "32529345",
      "name": "line-vertical-screen",
      "font_class": "line-vertical-screen",
      "unicode": "e8c9",
      "unicode_decimal": 59593
    },
    {
      "icon_id": "32529348",
      "name": "line-landscape",
      "font_class": "line-landscape",
      "unicode": "e915",
      "unicode_decimal": 59669
    },
    {
      "icon_id": "30092269",
      "name": "line-Live",
      "font_class": "line-Live",
      "unicode": "e872",
      "unicode_decimal": 59506
    },
    {
      "icon_id": "30082633",
      "name": "line-public",
      "font_class": "line-public1",
      "unicode": "e871",
      "unicode_decimal": 59505
    },
    {
      "icon_id": "29356415",
      "name": "line-Interactive tools",
      "font_class": "a-line-Interactivetools",
      "unicode": "e84d",
      "unicode_decimal": 59469
    },
    {
      "icon_id": "29356416",
      "name": "Videoroundtour",
      "font_class": "Videoroundtour",
      "unicode": "e86e",
      "unicode_decimal": 59502
    },
    {
      "icon_id": "29289572",
      "name": "tablets",
      "font_class": "tablets",
      "unicode": "e870",
      "unicode_decimal": 59504
    },
    {
      "icon_id": "29111026",
      "name": "delete",
      "font_class": "delete",
      "unicode": "e86f",
      "unicode_decimal": 59503
    },
    {
      "icon_id": "23719198",
      "name": "键盘_icon",
      "font_class": "jianpan_icon",
      "unicode": "e75b",
      "unicode_decimal": 59227
    },
    {
      "icon_id": "28768342",
      "name": "fill-off",
      "font_class": "fill-off",
      "unicode": "e792",
      "unicode_decimal": 59282
    },
    {
      "icon_id": "28708417",
      "name": "line-mixeroff",
      "font_class": "line-mixeroff",
      "unicode": "e78c",
      "unicode_decimal": 59276
    },
    {
      "icon_id": "28708418",
      "name": "color-mixer-on",
      "font_class": "color-mixer-on",
      "unicode": "e78d",
      "unicode_decimal": 59277
    },
    {
      "icon_id": "28708419",
      "name": "color-mixer-dc",
      "font_class": "color-mixer-dc",
      "unicode": "e78f",
      "unicode_decimal": 59279
    },
    {
      "icon_id": "28708420",
      "name": "line-mixer-on",
      "font_class": "line-mixer-on",
      "unicode": "e790",
      "unicode_decimal": 59280
    },
    {
      "icon_id": "28708421",
      "name": "color-video-dc",
      "font_class": "color-video-dc",
      "unicode": "e791",
      "unicode_decimal": 59281
    },
    {
      "icon_id": "28670981",
      "name": "line-document thumbnail",
      "font_class": "a-line-documentthumbnail",
      "unicode": "e855",
      "unicode_decimal": 59477
    },
    {
      "icon_id": "28644046",
      "name": "line-shangmai",
      "font_class": "line-shangmai",
      "unicode": "e840",
      "unicode_decimal": 59456
    },
    {
      "icon_id": "28644047",
      "name": "line-shangmaizhong",
      "font_class": "line-shangmaizhong",
      "unicode": "e841",
      "unicode_decimal": 59457
    },
    {
      "icon_id": "28644048",
      "name": "line-Online list",
      "font_class": "a-line-Onlinelist",
      "unicode": "e842",
      "unicode_decimal": 59458
    },
    {
      "icon_id": "28644049",
      "name": "line-blacklist",
      "font_class": "line-blacklist",
      "unicode": "e843",
      "unicode_decimal": 59459
    },
    {
      "icon_id": "28644050",
      "name": "line-Document to narrow",
      "font_class": "a-line-Documenttonarrow",
      "unicode": "e844",
      "unicode_decimal": 59460
    },
    {
      "icon_id": "28644051",
      "name": "line-zhi kan zhubanfang",
      "font_class": "a-line-zhikanzhubanfang",
      "unicode": "e845",
      "unicode_decimal": 59461
    },
    {
      "icon_id": "28644052",
      "name": "line-Upload document",
      "font_class": "a-line-Uploaddocument",
      "unicode": "e846",
      "unicode_decimal": 59462
    },
    {
      "icon_id": "28644053",
      "name": "line-My prize",
      "font_class": "a-line-Myprize",
      "unicode": "e847",
      "unicode_decimal": 59463
    },
    {
      "icon_id": "28644054",
      "name": "line-tag",
      "font_class": "line-tag",
      "unicode": "e848",
      "unicode_decimal": 59464
    },
    {
      "icon_id": "28644055",
      "name": "line-choose",
      "font_class": "line-choose",
      "unicode": "e849",
      "unicode_decimal": 59465
    },
    {
      "icon_id": "28644056",
      "name": "line-public",
      "font_class": "line-public",
      "unicode": "e84a",
      "unicode_decimal": 59466
    },
    {
      "icon_id": "28644057",
      "name": "line-1:1",
      "font_class": "a-line-11",
      "unicode": "e84b",
      "unicode_decimal": 59467
    },
    {
      "icon_id": "28644058",
      "name": "line-switch",
      "font_class": "line-switch",
      "unicode": "e84c",
      "unicode_decimal": 59468
    },
    {
      "icon_id": "28644060",
      "name": "line-drag",
      "font_class": "line-drag",
      "unicode": "e84e",
      "unicode_decimal": 59470
    },
    {
      "icon_id": "28644061",
      "name": "line-dissolution grouping",
      "font_class": "a-line-dissolutiongrouping",
      "unicode": "e84f",
      "unicode_decimal": 59471
    },
    {
      "icon_id": "28644062",
      "name": "line-Screen setting",
      "font_class": "a-line-Screensetting",
      "unicode": "e850",
      "unicode_decimal": 59472
    },
    {
      "icon_id": "28644063",
      "name": "line-batch distribution",
      "font_class": "a-line-batchdistribution",
      "unicode": "e851",
      "unicode_decimal": 59473
    },
    {
      "icon_id": "28644064",
      "name": "line-batch Change group",
      "font_class": "a-line-batchChangegroup",
      "unicode": "e852",
      "unicode_decimal": 59474
    },
    {
      "icon_id": "28644065",
      "name": "line-cancel speaker",
      "font_class": "a-line-cancelspeaker",
      "unicode": "e853",
      "unicode_decimal": 59475
    },
    {
      "icon_id": "28644066",
      "name": "line-timer",
      "font_class": "line-timer",
      "unicode": "e854",
      "unicode_decimal": 59476
    },
    {
      "icon_id": "28644068",
      "name": "line-View layout",
      "font_class": "a-line-Viewlayout",
      "unicode": "e856",
      "unicode_decimal": 59478
    },
    {
      "icon_id": "28644069",
      "name": "line-fictitious audience",
      "font_class": "a-line-fictitiousaudience",
      "unicode": "e857",
      "unicode_decimal": 59479
    },
    {
      "icon_id": "28644070",
      "name": "line-speaker1",
      "font_class": "line-speaker1",
      "unicode": "e858",
      "unicode_decimal": 59480
    },
    {
      "icon_id": "28644071",
      "name": "line-browser",
      "font_class": "line-browser",
      "unicode": "e859",
      "unicode_decimal": 59481
    },
    {
      "icon_id": "28644072",
      "name": "line-third party initiate",
      "font_class": "a-line-thirdpartyinitiate",
      "unicode": "e85a",
      "unicode_decimal": 59482
    },
    {
      "icon_id": "28644073",
      "name": "line-heat",
      "font_class": "line-heat",
      "unicode": "e85b",
      "unicode_decimal": 59483
    },
    {
      "icon_id": "28644074",
      "name": "line-Request assistance",
      "font_class": "a-line-Requestassistance",
      "unicode": "e85c",
      "unicode_decimal": 59484
    },
    {
      "icon_id": "28644075",
      "name": "line-speaker",
      "font_class": "line-speaker",
      "unicode": "e85d",
      "unicode_decimal": 59485
    },
    {
      "icon_id": "28644076",
      "name": "line-fingerprint",
      "font_class": "line-fingerprint",
      "unicode": "e85e",
      "unicode_decimal": 59486
    },
    {
      "icon_id": "28644077",
      "name": "line-On the microphone",
      "font_class": "a-line-Onthemicrophone",
      "unicode": "e85f",
      "unicode_decimal": 59487
    },
    {
      "icon_id": "28644078",
      "name": "line-Sign in",
      "font_class": "a-line-Signin",
      "unicode": "e860",
      "unicode_decimal": 59488
    },
    {
      "icon_id": "28644079",
      "name": "line-label",
      "font_class": "line-label",
      "unicode": "e861",
      "unicode_decimal": 59489
    },
    {
      "icon_id": "28644080",
      "name": "line-Desktop sharing",
      "font_class": "a-line-Desktopsharing",
      "unicode": "e862",
      "unicode_decimal": 59490
    },
    {
      "icon_id": "28644081",
      "name": "line-special set up",
      "font_class": "a-line-specialsetup",
      "unicode": "e863",
      "unicode_decimal": 59491
    },
    {
      "icon_id": "28644082",
      "name": "line-multilingual",
      "font_class": "line-multilingual",
      "unicode": "e864",
      "unicode_decimal": 59492
    },
    {
      "icon_id": "28644083",
      "name": "line-Into the team",
      "font_class": "a-line-Intotheteam",
      "unicode": "e865",
      "unicode_decimal": 59493
    },
    {
      "icon_id": "28644084",
      "name": "line-On the microphone1",
      "font_class": "a-line-Onthemicrophone1",
      "unicode": "e866",
      "unicode_decimal": 59494
    },
    {
      "icon_id": "28644085",
      "name": "line-cancel speaker1",
      "font_class": "a-line-cancelspeaker1",
      "unicode": "e867",
      "unicode_decimal": 59495
    },
    {
      "icon_id": "28644086",
      "name": "line-In group",
      "font_class": "a-line-Ingroup",
      "unicode": "e868",
      "unicode_decimal": 59496
    },
    {
      "icon_id": "28644087",
      "name": "line-Small program",
      "font_class": "a-line-Smallprogram",
      "unicode": "e869",
      "unicode_decimal": 59497
    },
    {
      "icon_id": "28644088",
      "name": "line-relay",
      "font_class": "line-relay",
      "unicode": "e86a",
      "unicode_decimal": 59498
    },
    {
      "icon_id": "28644089",
      "name": "line-whiteboard",
      "font_class": "line-whiteboard",
      "unicode": "e86b",
      "unicode_decimal": 59499
    },
    {
      "icon_id": "28644090",
      "name": "line-off the microphone",
      "font_class": "a-line-offthemicrophone",
      "unicode": "e86c",
      "unicode_decimal": 59500
    },
    {
      "icon_id": "28644091",
      "name": "line-Kicked out Members",
      "font_class": "a-line-KickedoutMembers",
      "unicode": "e86d",
      "unicode_decimal": 59501
    },
    {
      "icon_id": "26965173",
      "name": "icon_左右滑动@2x",
      "font_class": "a-icon_zuoyouhuadong2x",
      "unicode": "e78e",
      "unicode_decimal": 59278
    },
    {
      "icon_id": "27993804",
      "name": "line-browser",
      "font_class": "line-browser1",
      "unicode": "e7f9",
      "unicode_decimal": 59385
    },
    {
      "icon_id": "27970132",
      "name": "line-background",
      "font_class": "line-background",
      "unicode": "e7f2",
      "unicode_decimal": 59378
    },
    {
      "icon_id": "27965606",
      "name": "line-Skincare",
      "font_class": "line-Skincare",
      "unicode": "e7f1",
      "unicode_decimal": 59377
    },
    {
      "icon_id": "27938053",
      "name": "line-originalimage",
      "font_class": "line-originalimage",
      "unicode": "e7f0",
      "unicode_decimal": 59376
    },
    {
      "icon_id": "27937209",
      "name": "line-whitening",
      "font_class": "line-whitening",
      "unicode": "e7e4",
      "unicode_decimal": 59364
    },
    {
      "icon_id": "27937210",
      "name": "line-Thin face",
      "font_class": "a-line-Thinface",
      "unicode": "e7e5",
      "unicode_decimal": 59365
    },
    {
      "icon_id": "27937211",
      "name": "line-ruddy",
      "font_class": "line-ruddy",
      "unicode": "e7e6",
      "unicode_decimal": 59366
    },
    {
      "icon_id": "27937212",
      "name": "line-Brighteye",
      "font_class": "line-Brighteye",
      "unicode": "e7e7",
      "unicode_decimal": 59367
    },
    {
      "icon_id": "27937213",
      "name": "line-nose",
      "font_class": "line-nose",
      "unicode": "e7e9",
      "unicode_decimal": 59369
    },
    {
      "icon_id": "27937214",
      "name": "line-Bigeye",
      "font_class": "line-Bigeye",
      "unicode": "e7ea",
      "unicode_decimal": 59370
    },
    {
      "icon_id": "27937215",
      "name": "line-forehead",
      "font_class": "line-forehead",
      "unicode": "e7eb",
      "unicode_decimal": 59371
    },
    {
      "icon_id": "27937216",
      "name": "line-Beautytooth",
      "font_class": "line-Beautytooth",
      "unicode": "e7ec",
      "unicode_decimal": 59372
    },
    {
      "icon_id": "27937217",
      "name": "line-mouth",
      "font_class": "line-mouth",
      "unicode": "e7ed",
      "unicode_decimal": 59373
    },
    {
      "icon_id": "27937218",
      "name": "line-sharpen",
      "font_class": "line-sharpen",
      "unicode": "e7ee",
      "unicode_decimal": 59374
    },
    {
      "icon_id": "27937219",
      "name": "line-exfoliating",
      "font_class": "line-exfoliating",
      "unicode": "e7ef",
      "unicode_decimal": 59375
    },
    {
      "icon_id": "27900447",
      "name": "Red best",
      "font_class": "a-Redbest",
      "unicode": "e7e3",
      "unicode_decimal": 59363
    },
    {
      "icon_id": "27863738",
      "name": "color-try look",
      "font_class": "a-color-trylook",
      "unicode": "e634",
      "unicode_decimal": 58932
    },
    {
      "icon_id": "27863739",
      "name": "color-User statistics",
      "font_class": "a-color-Userstatistics",
      "unicode": "e63b",
      "unicode_decimal": 58939
    },
    {
      "icon_id": "27862834",
      "name": "color-advertising",
      "font_class": "color-advertising",
      "unicode": "e60b",
      "unicode_decimal": 58891
    },
    {
      "icon_id": "27862835",
      "name": "color-chat",
      "font_class": "color-chat",
      "unicode": "e60c",
      "unicode_decimal": 58892
    },
    {
      "icon_id": "27862836",
      "name": "color-client initiate",
      "font_class": "a-color-clientinitiate",
      "unicode": "e60d",
      "unicode_decimal": 58893
    },
    {
      "icon_id": "27862837",
      "name": "color-child account",
      "font_class": "a-color-childaccount",
      "unicode": "e60e",
      "unicode_decimal": 58894
    },
    {
      "icon_id": "27862838",
      "name": "color-Banned chat",
      "font_class": "a-color-Bannedchat",
      "unicode": "e60f",
      "unicode_decimal": 58895
    },
    {
      "icon_id": "27862839",
      "name": "color-Brand set",
      "font_class": "a-color-Brandset",
      "unicode": "e610",
      "unicode_decimal": 58896
    },
    {
      "icon_id": "27862840",
      "name": "color-Custom menu",
      "font_class": "a-color-Custommenu",
      "unicode": "e611",
      "unicode_decimal": 58897
    },
    {
      "icon_id": "27862841",
      "name": "color-concurrent",
      "font_class": "color-concurrent",
      "unicode": "e612",
      "unicode_decimal": 58898
    },
    {
      "icon_id": "27862842",
      "name": "color-console logo",
      "font_class": "a-color-consolelogo",
      "unicode": "e613",
      "unicode_decimal": 58899
    },
    {
      "icon_id": "27862843",
      "name": "color-document",
      "font_class": "color-document",
      "unicode": "e614",
      "unicode_decimal": 58900
    },
    {
      "icon_id": "27862844",
      "name": "color-development Set up",
      "font_class": "a-color-developmentSetup",
      "unicode": "e615",
      "unicode_decimal": 58901
    },
    {
      "icon_id": "27862845",
      "name": "color-gift",
      "font_class": "color-gift",
      "unicode": "e616",
      "unicode_decimal": 58902
    },
    {
      "icon_id": "27862846",
      "name": "color-grouping  live",
      "font_class": "a-color-groupinglive",
      "unicode": "e617",
      "unicode_decimal": 58903
    },
    {
      "icon_id": "27862847",
      "name": "color-goods",
      "font_class": "color-goods",
      "unicode": "e618",
      "unicode_decimal": 58904
    },
    {
      "icon_id": "27862848",
      "name": "color-Data report",
      "font_class": "a-color-Datareport",
      "unicode": "e619",
      "unicode_decimal": 58905
    },
    {
      "icon_id": "27862849",
      "name": "color-Functional configuration",
      "font_class": "a-color-Functionalconfiguration",
      "unicode": "e61a",
      "unicode_decimal": 58906
    },
    {
      "icon_id": "27862850",
      "name": "color-give a like",
      "font_class": "a-color-givealike",
      "unicode": "e61b",
      "unicode_decimal": 58907
    },
    {
      "icon_id": "27862851",
      "name": "color-lian mai",
      "font_class": "a-color-lianmai",
      "unicode": "e61c",
      "unicode_decimal": 58908
    },
    {
      "icon_id": "27862852",
      "name": "color-information",
      "font_class": "color-information",
      "unicode": "e61d",
      "unicode_decimal": 58909
    },
    {
      "icon_id": "27862853",
      "name": "color-invitation card",
      "font_class": "a-color-invitationcard",
      "unicode": "e61e",
      "unicode_decimal": 58910
    },
    {
      "icon_id": "27862854",
      "name": "color-Opening the posters",
      "font_class": "a-color-Openingtheposters",
      "unicode": "e61f",
      "unicode_decimal": 58911
    },
    {
      "icon_id": "27862855",
      "name": "color-Playback management",
      "font_class": "a-color-Playbackmanagement",
      "unicode": "e620",
      "unicode_decimal": 58912
    },
    {
      "icon_id": "27862856",
      "name": "color-Interactive statistical",
      "font_class": "a-color-Interactivestatistical",
      "unicode": "e621",
      "unicode_decimal": 58913
    },
    {
      "icon_id": "27862857",
      "name": "color-Player Settings",
      "font_class": "a-color-PlayerSettings",
      "unicode": "e622",
      "unicode_decimal": 58914
    },
    {
      "icon_id": "27862858",
      "name": "color-Lucky draw",
      "font_class": "a-color-Luckydraw",
      "unicode": "e623",
      "unicode_decimal": 58915
    },
    {
      "icon_id": "27862859",
      "name": "color-official account",
      "font_class": "a-color-officialaccount",
      "unicode": "e624",
      "unicode_decimal": 58916
    },
    {
      "icon_id": "27862860",
      "name": "color-playback",
      "font_class": "color-playback",
      "unicode": "e625",
      "unicode_decimal": 58917
    },
    {
      "icon_id": "27862861",
      "name": "color-Question",
      "font_class": "color-Question",
      "unicode": "e626",
      "unicode_decimal": 58918
    },
    {
      "icon_id": "27862862",
      "name": "color-red packet",
      "font_class": "a-color-redpacket",
      "unicode": "e627",
      "unicode_decimal": 58919
    },
    {
      "icon_id": "27862863",
      "name": "color-registration form",
      "font_class": "a-color-registrationform",
      "unicode": "e628",
      "unicode_decimal": 58920
    },
    {
      "icon_id": "27862864",
      "name": "color-Invite ranking",
      "font_class": "a-color-Inviteranking",
      "unicode": "e629",
      "unicode_decimal": 58921
    },
    {
      "icon_id": "27862865",
      "name": "color-Role to invite",
      "font_class": "a-color-Roletoinvite",
      "unicode": "e62a",
      "unicode_decimal": 58922
    },
    {
      "icon_id": "27862866",
      "name": "color-questionnaire",
      "font_class": "color-questionnaire",
      "unicode": "e62b",
      "unicode_decimal": 58923
    },
    {
      "icon_id": "27862867",
      "name": "color-share ranking",
      "font_class": "a-color-shareranking",
      "unicode": "e62c",
      "unicode_decimal": 58924
    },
    {
      "icon_id": "27862868",
      "name": "color-Reward",
      "font_class": "color-Reward",
      "unicode": "e62d",
      "unicode_decimal": 58925
    },
    {
      "icon_id": "27862869",
      "name": "color-Sign in",
      "font_class": "a-color-Signin",
      "unicode": "e62e",
      "unicode_decimal": 58926
    },
    {
      "icon_id": "27862870",
      "name": "color-Promotion of the embedded",
      "font_class": "a-color-Promotionoftheembedded",
      "unicode": "e62f",
      "unicode_decimal": 58927
    },
    {
      "icon_id": "27862871",
      "name": "color-share",
      "font_class": "color-share",
      "unicode": "e630",
      "unicode_decimal": 58928
    },
    {
      "icon_id": "27862872",
      "name": "color-Spot file",
      "font_class": "a-color-Spotfile",
      "unicode": "e631",
      "unicode_decimal": 58929
    },
    {
      "icon_id": "27862873",
      "name": "color-To make an appointment",
      "font_class": "a-color-Tomakeanappointment",
      "unicode": "e632",
      "unicode_decimal": 58930
    },
    {
      "icon_id": "27862874",
      "name": "color-traffic",
      "font_class": "color-traffic",
      "unicode": "e633",
      "unicode_decimal": 58931
    },
    {
      "icon_id": "27862876",
      "name": "color-Video limit",
      "font_class": "a-color-Videolimit",
      "unicode": "e635",
      "unicode_decimal": 58933
    },
    {
      "icon_id": "27862877",
      "name": "color-video",
      "font_class": "color-video",
      "unicode": "e636",
      "unicode_decimal": 58934
    },
    {
      "icon_id": "27862878",
      "name": "color-Video management",
      "font_class": "a-color-Videomanagement",
      "unicode": "e637",
      "unicode_decimal": 58935
    },
    {
      "icon_id": "27862879",
      "name": "color-web page initiate",
      "font_class": "a-color-webpageinitiate",
      "unicode": "e638",
      "unicode_decimal": 58936
    },
    {
      "icon_id": "27862880",
      "name": "color-web page initiate1",
      "font_class": "a-color-webpageinitiate1",
      "unicode": "e639",
      "unicode_decimal": 58937
    },
    {
      "icon_id": "27862881",
      "name": "color-virtual number",
      "font_class": "a-color-virtualnumber",
      "unicode": "e63a",
      "unicode_decimal": 58938
    },
    {
      "icon_id": "9156117",
      "name": "页面错误",
      "font_class": "yemiancuowu",
      "unicode": "e69e",
      "unicode_decimal": 59038
    },
    {
      "icon_id": "9555811",
      "name": "课件准备中",
      "font_class": "kejianzhunbeizhong",
      "unicode": "e72d",
      "unicode_decimal": 59181
    },
    {
      "icon_id": "9555812",
      "name": "暂无文档",
      "font_class": "zanwuwendang",
      "unicode": "e72e",
      "unicode_decimal": 59182
    },
    {
      "icon_id": "9555813",
      "name": "直播结束",
      "font_class": "zhibojieshu",
      "unicode": "e72f",
      "unicode_decimal": 59183
    },
    {
      "icon_id": "9833358",
      "name": "未直播占位图",
      "font_class": "weizhibozhanweitu",
      "unicode": "e763",
      "unicode_decimal": 59235
    },
    {
      "icon_id": "14150702",
      "name": "暂无举手",
      "font_class": "zanwujushou",
      "unicode": "e7e1",
      "unicode_decimal": 59361
    },
    {
      "icon_id": "14150703",
      "name": "暂无成员",
      "font_class": "zanwuchengyuan",
      "unicode": "e7e2",
      "unicode_decimal": 59362
    },
    {
      "icon_id": "14150704",
      "name": "暂无搜索",
      "font_class": "zanwusousuo",
      "unicode": "e7e8",
      "unicode_decimal": 59368
    }
  ]
}
